cytomat/__init__.py
cytomat/barcode_scanner.py
cytomat/climate_controller.py
cytomat/cytomat.py
cytomat/errors.py
cytomat/maintenance_controller.py
cytomat/plate_handler.py
cytomat/serial_port.py
cytomat/shaker_controller.py
cytomat/status.py
cytomat/swap_station.py
cytomat/utils.py
open_cytomat_plus-0.1.4.dist-info/LICENSE
open_cytomat_plus-0.1.4.dist-info/METADATA
open_cytomat_plus-0.1.4.dist-info/WHEEL
open_cytomat_plus-0.1.4.dist-info/RECORD
