Metadata-Version: 2.1
Name: open-cytomat-plus
Version: 0.1.4
Summary: 
Author: Niklas Mertsch
Author-email: niklas.mertsch@stud.uni-goettingen.de
Requires-Python: >=3.10,<4.0
Classifier: Programming Language :: Python :: 3
Classifier: Programming Language :: Python :: 3.10
Classifier: Programming Language :: Python :: 3.11
Classifier: Programming Language :: Python :: 3.12
Requires-Dist: pyserial (>=3.5,<4.0)
